{
 "Alpha-3 code":"UMC",
 "Country or Area":"Upper-middle-income countries",
 "Latitude (average)":0.0,
 "Longitude (average)":0.0,
 "Group 1":"",
 "Group 2":"",
 "LDC":false,
 "LLDC":false,
 "SIDS":false,
 "Income group":"",
 "indicators":[
  {
   "indicator":"% change in remittance from previous year",
   "yearlyData":[
    {
     "year":1980,
     "value":"5092038218.2812"
    },
    {
     "year":1981,
     "value":"6119829607.7179"
    },
    {
     "year":1982,
     "value":"6382085512.1979"
    },
    {
     "year":1983,
     "value":"6026215820.7145"
    },
    {
     "year":1984,
     "value":"6554624865.0239"
    },
    {
     "year":1985,
     "value":"6252981242.4544"
    },
    {
     "year":1986,
     "value":"6886378494.0974"
    },
    {
     "year":1987,
     "value":"7432335650.3061"
    },
    {
     "year":1988,
     "value":"7741595253.9471"
    },
    {
     "year":1989,
     "value":"9274258388.5592"
    },
    {
     "year":1990,
     "value":"10500194405.3552"
    },
    {
     "year":1991,
     "value":"11116755267.148998"
    },
    {
     "year":1992,
     "value":"12874777321.606"
    },
    {
     "year":1993,
     "value":"14131233156.6766"
    },
    {
     "year":1994,
     "value":"21017825857.3842"
    },
    {
     "year":1995,
     "value":"19231734904.5283"
    },
    {
     "year":1996,
     "value":"21481462952.7104"
    },
    {
     "year":1997,
     "value":"25959572678.4451"
    },
    {
     "year":1998,
     "value":"26054726181.9075"
    },
    {
     "year":1999,
     "value":"27216595132.3319"
    },
    {
     "year":2000,
     "value":"29760054671.5761"
    },
    {
     "year":2001,
     "value":"33246770343.4123"
    },
    {
     "year":2002,
     "value":"37756379956.1935"
    },
    {
     "year":2003,
     "value":"48745879282.9808"
    },
    {
     "year":2004,
     "value":"59946986650.2567"
    },
    {
     "year":2005,
     "value":"65388422362.3006"
    },
    {
     "year":2006,
     "value":"76333064029.9517"
    },
    {
     "year":2007,
     "value":"90029227454.6116"
    },
    {
     "year":2008,
     "value":"96519715603.6215"
    },
    {
     "year":2009,
     "value":"89165926121.61699"
    },
    {
     "year":2010,
     "value":"95642354196.5501"
    },
    {
     "year":2011,
     "value":"104900840038.723"
    },
    {
     "year":2012,
     "value":"105569556608.416"
    },
    {
     "year":2013,
     "value":"112294049210.145"
    },
    {
     "year":2014,
     "value":"128736938129.905"
    },
    {
     "year":2015,
     "value":"129032558297.209"
    },
    {
     "year":2016,
     "value":"125228283069.651"
    },
    {
     "year":2017,
     "value":"138722722873.99402"
    },
    {
     "year":2018,
     "value":"145156525538.954"
    },
    {
     "year":2019,
     "value":"147329697731.53302"
    },
    {
     "year":2020,
     "value":"151625272707.999"
    },
    {
     "year":2021,
     "value":"182261709631.823"
    },
    {
     "year":2022,
     "value":"220882936152.155"
    }
   ]
  },
  {
   "indicator":"Access to electricity, rural (% of rural population)",
   "yearlyData":[
    {
     "year":2000,
     "value":"92.14781199821232"
    },
    {
     "year":2012,
     "value":"98.36115551239443"
    },
    {
     "year":2013,
     "value":"98.46188749965404"
    },
    {
     "year":2014,
     "value":"98.54768102985743"
    },
    {
     "year":2015,
     "value":"98.64819543228757"
    },
    {
     "year":2016,
     "value":"98.63498934866851"
    },
    {
     "year":2017,
     "value":"98.83440700887172"
    },
    {
     "year":2018,
     "value":"98.74760983136864"
    },
    {
     "year":2019,
     "value":"98.86830578253523"
    },
    {
     "year":2020,
     "value":"99.01456408037704"
    }
   ]
  },
  {
   "indicator":"Access to electricity, urban (% of urban population)",
   "yearlyData":[
    {
     "year":2000,
     "value":"99.08127594357364"
    },
    {
     "year":2012,
     "value":"99.53349654984136"
    },
    {
     "year":2013,
     "value":"99.57036750460924"
    },
    {
     "year":2014,
     "value":"99.57141983913635"
    },
    {
     "year":2015,
     "value":"99.22293774889826"
    },
    {
     "year":2016,
     "value":"99.59918029702986"
    },
    {
     "year":2017,
     "value":"99.6309291521646"
    },
    {
     "year":2018,
     "value":"99.62286856383403"
    },
    {
     "year":2019,
     "value":"99.654358975327"
    },
    {
     "year":2020,
     "value":"99.6701967751239"
    }
   ]
  },
  {
   "indicator":"Access to electricity (% of population)",
   "yearlyData":[
    {
     "year":2000,
     "value":"95.56768527821728"
    },
    {
     "year":2012,
     "value":"99.02041772669001"
    },
    {
     "year":2013,
     "value":"99.08652188823551"
    },
    {
     "year":2014,
     "value":"99.12396644735658"
    },
    {
     "year":2015,
     "value":"98.89317977411177"
    },
    {
     "year":2016,
     "value":"99.18291983549896"
    },
    {
     "year":2017,
     "value":"99.2678057530108"
    },
    {
     "year":2018,
     "value":"99.23881836626205"
    },
    {
     "year":2019,
     "value":"99.31084765851696"
    },
    {
     "year":2020,
     "value":"99.37683822298838"
    }
   ]
  },
  {
   "indicator":"Access to clean fuels and technologies for cooking  (% of population)",
   "yearlyData":[
    {
     "year":2000,
     "value":"58.293947972720545"
    },
    {
     "year":2012,
     "value":"72.55075114205438"
    },
    {
     "year":2013,
     "value":"74.15249590435383"
    },
    {
     "year":2014,
     "value":"75.89637303707094"
    },
    {
     "year":2015,
     "value":"77.37347994225907"
    },
    {
     "year":2016,
     "value":"78.76959454042212"
    },
    {
     "year":2017,
     "value":"80.29860783517042"
    },
    {
     "year":2018,
     "value":"81.7346739536444"
    },
    {
     "year":2019,
     "value":"82.91963039187715"
    },
    {
     "year":2020,
     "value":"83.98243863522192"
    }
   ]
  },
  {
   "indicator":"Individuals using the Internet (% of population)",
   "yearlyData":[
    {
     "year":1990,
     "value":"0.0"
    },
    {
     "year":1991,
     "value":"0.000783088273298456"
    },
    {
     "year":1992,
     "value":"0.0027168876406741"
    },
    {
     "year":1993,
     "value":"0.00832564113917488"
    },
    {
     "year":1994,
     "value":"0.0217417219392817"
    },
    {
     "year":1995,
     "value":"0.0541548983469174"
    },
    {
     "year":1996,
     "value":"0.128155201148544"
    },
    {
     "year":1997,
     "value":"0.26539176338174103"
    },
    {
     "year":1998,
     "value":"0.6058130263373129"
    },
    {
     "year":1999,
     "value":"1.27886609021521"
    },
    {
     "year":2000,
     "value":"2.54626286263058"
    },
    {
     "year":2001,
     "value":"3.6750467805911295"
    },
    {
     "year":2002,
     "value":"6.05123478951025"
    },
    {
     "year":2003,
     "value":"7.94866286897506"
    },
    {
     "year":2004,
     "value":"9.98874760382827"
    },
    {
     "year":2005,
     "value":"11.565645143559301"
    },
    {
     "year":2006,
     "value":"14.133399793906"
    },
    {
     "year":2007,
     "value":"18.9379282687017"
    },
    {
     "year":2008,
     "value":"24.0888575317164"
    },
    {
     "year":2009,
     "value":"29.728258565510107"
    },
    {
     "year":2010,
     "value":"34.7877200369872"
    },
    {
     "year":2011,
     "value":"39.3542570379902"
    },
    {
     "year":2012,
     "value":"43.50252699215079"
    },
    {
     "year":2013,
     "value":"46.63040950275471"
    },
    {
     "year":2014,
     "value":"49.2196276975073"
    },
    {
     "year":2015,
     "value":"52.4510495661857"
    },
    {
     "year":2016,
     "value":"55.6885931467165"
    },
    {
     "year":2017,
     "value":"57.761887805491895"
    },
    {
     "year":2018,
     "value":"62.3877597421772"
    },
    {
     "year":2019,
     "value":"67.3492117680259"
    },
    {
     "year":2020,
     "value":"72.7520222041998"
    },
    {
     "year":2021,
     "value":"75.716978670356"
    }
   ]
  },
  {
   "indicator":"People using safely managed drinking water services (% of population)",
   "yearlyData":[
    {
     "year":2000,
     "value":"68.3859169276999"
    },
    {
     "year":2001,
     "value":"68.5376494508619"
    },
    {
     "year":2002,
     "value":"69.0087449460813"
    },
    {
     "year":2003,
     "value":"69.4687822714675"
    },
    {
     "year":2004,
     "value":"69.9152772888151"
    },
    {
     "year":2005,
     "value":"70.3529959270946"
    },
    {
     "year":2006,
     "value":"70.78618547372591"
    },
    {
     "year":2007,
     "value":"71.197753211903"
    },
    {
     "year":2008,
     "value":"71.5943889264543"
    },
    {
     "year":2009,
     "value":"71.9743324720262"
    },
    {
     "year":2010,
     "value":"72.2883864369181"
    },
    {
     "year":2011,
     "value":"72.5810789072701"
    },
    {
     "year":2012,
     "value":"72.85412176424971"
    },
    {
     "year":2013,
     "value":"73.251934807428"
    },
    {
     "year":2014,
     "value":"73.63625450494679"
    },
    {
     "year":2015,
     "value":"74.009205782261"
    },
    {
     "year":2016,
     "value":"74.3663196008786"
    },
    {
     "year":2017,
     "value":"74.7181308981567"
    },
    {
     "year":2018,
     "value":"75.04869008549271"
    },
    {
     "year":2019,
     "value":"75.3559112525346"
    },
    {
     "year":2020,
     "value":"75.641526334636"
    }
   ]
  },
  {
   "indicator":"Primary energy consumption from coal, measured in terawatt-hours",
   "yearlyData":[
    {
     "year":1980,
     "value":"8434.929"
    },
    {
     "year":1981,
     "value":"8490.438"
    },
    {
     "year":1982,
     "value":"8832.263"
    },
    {
     "year":1983,
     "value":"9163.992"
    },
    {
     "year":1984,
     "value":"9558.742"
    },
    {
     "year":1985,
     "value":"8890.304"
    },
    {
     "year":1986,
     "value":"9227.734"
    },
    {
     "year":1987,
     "value":"9759.784"
    },
    {
     "year":1988,
     "value":"10200.985"
    },
    {
     "year":1989,
     "value":"10369.803"
    },
    {
     "year":1990,
     "value":"10206.226"
    },
    {
     "year":1991,
     "value":"10309.848"
    },
    {
     "year":1992,
     "value":"10510.228"
    },
    {
     "year":1993,
     "value":"10729.959"
    },
    {
     "year":1994,
     "value":"11028.705"
    },
    {
     "year":1995,
     "value":"11057.254"
    },
    {
     "year":1996,
     "value":"11417.032"
    },
    {
     "year":1997,
     "value":"11159.508999999998"
    },
    {
     "year":1998,
     "value":"10959.006"
    },
    {
     "year":1999,
     "value":"11169.608"
    },
    {
     "year":2000,
     "value":"11358.208"
    },
    {
     "year":2001,
     "value":"11790.956"
    },
    {
     "year":2002,
     "value":"12657.351"
    },
    {
     "year":2003,
     "value":"14636.152"
    },
    {
     "year":2004,
     "value":"16611.803"
    },
    {
     "year":2005,
     "value":"18747.713"
    },
    {
     "year":2006,
     "value":"20431.086"
    },
    {
     "year":2007,
     "value":"22044.539"
    },
    {
     "year":2008,
     "value":"22578.252"
    },
    {
     "year":2009,
     "value":"23285.395"
    },
    {
     "year":2010,
     "value":"24156.611"
    },
    {
     "year":2011,
     "value":"26093.957"
    },
    {
     "year":2012,
     "value":"26430.85"
    },
    {
     "year":2013,
     "value":"26729.064"
    },
    {
     "year":2014,
     "value":"26811.027"
    },
    {
     "year":2015,
     "value":"26335.715"
    },
    {
     "year":2016,
     "value":"26194.461"
    },
    {
     "year":2017,
     "value":"26318.141"
    },
    {
     "year":2018,
     "value":"26502.131"
    },
    {
     "year":2019,
     "value":"26674.111"
    },
    {
     "year":2020,
     "value":"26582.701"
    },
    {
     "year":2021,
     "value":"27708.553"
    }
   ]
  },
  {
   "indicator":"Electricity generation from coal, measured in terawatt-hours",
   "yearlyData":[
    {
     "year":1985,
     "value":"623.226"
    },
    {
     "year":1986,
     "value":"680.547"
    },
    {
     "year":1987,
     "value":"734.5939999999998"
    },
    {
     "year":1988,
     "value":"765.332"
    },
    {
     "year":1989,
     "value":"815.555"
    },
    {
     "year":1990,
     "value":"863.421"
    },
    {
     "year":1991,
     "value":"925.191"
    },
    {
     "year":1992,
     "value":"996.575"
    },
    {
     "year":1993,
     "value":"1017.691"
    },
    {
     "year":1994,
     "value":"1140.448"
    },
    {
     "year":1995,
     "value":"1193.769"
    },
    {
     "year":1996,
     "value":"1290.501"
    },
    {
     "year":1997,
     "value":"1337.068"
    },
    {
     "year":1998,
     "value":"1361.442"
    },
    {
     "year":1999,
     "value":"1440.725"
    },
    {
     "year":2000,
     "value":"1611.01"
    },
    {
     "year":2001,
     "value":"1692.74"
    },
    {
     "year":2002,
     "value":"1849.17"
    },
    {
     "year":2003,
     "value":"2124.52"
    },
    {
     "year":2004,
     "value":"2336.64"
    },
    {
     "year":2005,
     "value":"2622.15"
    },
    {
     "year":2006,
     "value":"2976.98"
    },
    {
     "year":2007,
     "value":"3358.93"
    },
    {
     "year":2008,
     "value":"3437.18"
    },
    {
     "year":2009,
     "value":"3600.14"
    },
    {
     "year":2010,
     "value":"3958.11"
    },
    {
     "year":2011,
     "value":"4451.92"
    },
    {
     "year":2012,
     "value":"4505.46"
    },
    {
     "year":2013,
     "value":"4817.31"
    },
    {
     "year":2014,
     "value":"4951.99"
    },
    {
     "year":2015,
     "value":"4801.19"
    },
    {
     "year":2016,
     "value":"4944.74"
    },
    {
     "year":2017,
     "value":"5233.5"
    },
    {
     "year":2018,
     "value":"5597.0"
    },
    {
     "year":2019,
     "value":"5691.41"
    },
    {
     "year":2020,
     "value":"5712.03"
    },
    {
     "year":2021,
     "value":"6144.71"
    }
   ]
  },
  {
   "indicator":"Current health expenditure (% of GDP)",
   "yearlyData":[
    {
     "year":2000,
     "value":"6.01"
    },
    {
     "year":2001,
     "value":"5.94"
    },
    {
     "year":2002,
     "value":"5.97"
    },
    {
     "year":2003,
     "value":"5.89"
    },
    {
     "year":2004,
     "value":"5.92"
    },
    {
     "year":2005,
     "value":"5.98"
    },
    {
     "year":2006,
     "value":"5.99"
    },
    {
     "year":2007,
     "value":"5.96"
    },
    {
     "year":2008,
     "value":"6.09"
    },
    {
     "year":2009,
     "value":"6.4"
    },
    {
     "year":2010,
     "value":"6.29"
    },
    {
     "year":2011,
     "value":"6.2"
    },
    {
     "year":2012,
     "value":"6.22"
    },
    {
     "year":2013,
     "value":"6.28"
    },
    {
     "year":2014,
     "value":"6.35"
    },
    {
     "year":2015,
     "value":"6.57"
    },
    {
     "year":2016,
     "value":"6.57"
    },
    {
     "year":2017,
     "value":"6.56"
    },
    {
     "year":2018,
     "value":"6.61"
    },
    {
     "year":2019,
     "value":"6.79"
    },
    {
     "year":2020,
     "value":"7.46"
    }
   ]
  },
  {
   "indicator":"Renewable energy consumption (% of total final energy consumption)",
   "yearlyData":[
    {
     "year":1990,
     "value":"19.952895739419123"
    },
    {
     "year":2000,
     "value":"20.94651630409783"
    },
    {
     "year":2012,
     "value":"13.153642382687881"
    },
    {
     "year":2013,
     "value":"13.205258136009308"
    },
    {
     "year":2014,
     "value":"13.447062313167677"
    },
    {
     "year":2015,
     "value":"13.665184982435706"
    }
   ]
  },
  {
   "indicator":"Energy imports, net (% of energy use)",
   "yearlyData":[
    {
     "year":1990,
     "value":"-23.74367289179739"
    },
    {
     "year":2000,
     "value":"-24.007833505946074"
    },
    {
     "year":2012,
     "value":"-8.90517385004234"
    },
    {
     "year":2013,
     "value":"-7.925181778063457"
    },
    {
     "year":2014,
     "value":"-6.728703828615617"
    },
    {
     "year":2015,
     "value":"28.00817540414526"
    }
   ]
  },
  {
   "indicator":"Employment in agriculture (% of total employment)",
   "yearlyData":[
    {
     "year":1991,
     "value":"48.447035944572704"
    },
    {
     "year":1992,
     "value":"47.66044000786329"
    },
    {
     "year":1993,
     "value":"46.1150117232988"
    },
    {
     "year":1994,
     "value":"44.7355650705913"
    },
    {
     "year":1995,
     "value":"43.2589185330066"
    },
    {
     "year":1996,
     "value":"42.0098696000462"
    },
    {
     "year":1997,
     "value":"41.5718294857575"
    },
    {
     "year":1998,
     "value":"41.36295718479271"
    },
    {
     "year":1999,
     "value":"41.64675876102479"
    },
    {
     "year":2000,
     "value":"41.2793055066291"
    },
    {
     "year":2001,
     "value":"40.9097455688812"
    },
    {
     "year":2002,
     "value":"40.6688568868461"
    },
    {
     "year":2003,
     "value":"39.8675724429313"
    },
    {
     "year":2004,
     "value":"37.9212086107084"
    },
    {
     "year":2005,
     "value":"36.2874278611343"
    },
    {
     "year":2006,
     "value":"34.585237354380496"
    },
    {
     "year":2007,
     "value":"33.0357603666248"
    },
    {
     "year":2008,
     "value":"32.0707196081369"
    },
    {
     "year":2009,
     "value":"30.9822696400137"
    },
    {
     "year":2010,
     "value":"29.871686570093694"
    },
    {
     "year":2011,
     "value":"28.6725781980714"
    },
    {
     "year":2012,
     "value":"27.7052598729816"
    },
    {
     "year":2013,
     "value":"26.017535968827"
    },
    {
     "year":2014,
     "value":"24.413974068211107"
    },
    {
     "year":2015,
     "value":"23.7249128977768"
    },
    {
     "year":2016,
     "value":"23.070224264214506"
    },
    {
     "year":2017,
     "value":"22.508762678137106"
    },
    {
     "year":2018,
     "value":"21.8106518787064"
    },
    {
     "year":2019,
     "value":"21.1996848673493"
    },
    {
     "year":2020,
     "value":"21.2464882936364"
    },
    {
     "year":2021,
     "value":"20.8133871615533"
    }
   ]
  },
  {
   "indicator":"Employment in industry (% of total employment)",
   "yearlyData":[
    {
     "year":1991,
     "value":"22.7074257738376"
    },
    {
     "year":1992,
     "value":"22.816554834188103"
    },
    {
     "year":1993,
     "value":"23.197270730300197"
    },
    {
     "year":1994,
     "value":"23.2689937924992"
    },
    {
     "year":1995,
     "value":"23.4086993951402"
    },
    {
     "year":1996,
     "value":"23.710635654583808"
    },
    {
     "year":1997,
     "value":"23.7812956126549"
    },
    {
     "year":1998,
     "value":"23.548716689337397"
    },
    {
     "year":1999,
     "value":"23.1799920025695"
    },
    {
     "year":2000,
     "value":"22.9501133890723"
    },
    {
     "year":2001,
     "value":"22.751590547656498"
    },
    {
     "year":2002,
     "value":"22.1768261899863"
    },
    {
     "year":2003,
     "value":"22.2465395609376"
    },
    {
     "year":2004,
     "value":"22.9509749366045"
    },
    {
     "year":2005,
     "value":"23.866904658385202"
    },
    {
     "year":2006,
     "value":"24.783853729218503"
    },
    {
     "year":2007,
     "value":"25.917769600833395"
    },
    {
     "year":2008,
     "value":"26.037775720874"
    },
    {
     "year":2009,
     "value":"26.137141533133697"
    },
    {
     "year":2010,
     "value":"26.7292359720482"
    },
    {
     "year":2011,
     "value":"27.1229624617873"
    },
    {
     "year":2012,
     "value":"27.6630851908948"
    },
    {
     "year":2013,
     "value":"27.567891123419102"
    },
    {
     "year":2014,
     "value":"27.550823599959198"
    },
    {
     "year":2015,
     "value":"27.012389039984694"
    },
    {
     "year":2016,
     "value":"26.6476322070635"
    },
    {
     "year":2017,
     "value":"26.114434874659"
    },
    {
     "year":2018,
     "value":"25.7667942358216"
    },
    {
     "year":2019,
     "value":"25.5480462538015"
    },
    {
     "year":2020,
     "value":"25.7291667340986"
    },
    {
     "year":2021,
     "value":"26.162847516061397"
    }
   ]
  },
  {
   "indicator":"Employment in services (% of total employment)",
   "yearlyData":[
    {
     "year":1991,
     "value":"28.845539252630505"
    },
    {
     "year":1992,
     "value":"29.523007488183303"
    },
    {
     "year":1993,
     "value":"30.6877055870957"
    },
    {
     "year":1994,
     "value":"31.995441710372802"
    },
    {
     "year":1995,
     "value":"33.3323756787931"
    },
    {
     "year":1996,
     "value":"34.2795001321079"
    },
    {
     "year":1997,
     "value":"34.6468872099325"
    },
    {
     "year":1998,
     "value":"35.0883236388082"
    },
    {
     "year":1999,
     "value":"35.1732480519026"
    },
    {
     "year":2000,
     "value":"35.770579925088605"
    },
    {
     "year":2001,
     "value":"36.3386717121012"
    },
    {
     "year":2002,
     "value":"37.1543242233305"
    },
    {
     "year":2003,
     "value":"37.8858878234146"
    },
    {
     "year":2004,
     "value":"39.1278097179186"
    },
    {
     "year":2005,
     "value":"39.8456567303199"
    },
    {
     "year":2006,
     "value":"40.630911326249795"
    },
    {
     "year":2007,
     "value":"41.0464740971616"
    },
    {
     "year":2008,
     "value":"41.8914989568081"
    },
    {
     "year":2009,
     "value":"42.880582099805395"
    },
    {
     "year":2010,
     "value":"43.39907891327599"
    },
    {
     "year":2011,
     "value":"44.204470240906886"
    },
    {
     "year":2012,
     "value":"44.6316693586223"
    },
    {
     "year":2013,
     "value":"46.4145685849164"
    },
    {
     "year":2014,
     "value":"48.03520422314"
    },
    {
     "year":2015,
     "value":"49.2626935495992"
    },
    {
     "year":2016,
     "value":"50.282138719978505"
    },
    {
     "year":2017,
     "value":"51.3767955077474"
    },
    {
     "year":2018,
     "value":"52.422554020739"
    },
    {
     "year":2019,
     "value":"53.2522676979766"
    },
    {
     "year":2020,
     "value":"53.0243456029111"
    },
    {
     "year":2021,
     "value":"53.0237597237333"
    }
   ]
  },
  {
   "indicator":"Primary energy consumption per capita, measured in kilowatt-hours",
   "yearlyData":[
    {
     "year":1980,
     "value":"13991.819"
    },
    {
     "year":1981,
     "value":"14002.123"
    },
    {
     "year":1982,
     "value":"14219.551"
    },
    {
     "year":1983,
     "value":"14395.432"
    },
    {
     "year":1984,
     "value":"14848.546"
    },
    {
     "year":1985,
     "value":"12907.186000000003"
    },
    {
     "year":1986,
     "value":"13133.433"
    },
    {
     "year":1987,
     "value":"13512.109"
    },
    {
     "year":1988,
     "value":"13831.261"
    },
    {
     "year":1989,
     "value":"13868.025"
    },
    {
     "year":1990,
     "value":"13656.999"
    },
    {
     "year":1991,
     "value":"13574.821000000002"
    },
    {
     "year":1992,
     "value":"13510.244"
    },
    {
     "year":1993,
     "value":"13429.258"
    },
    {
     "year":1994,
     "value":"13288.491000000002"
    },
    {
     "year":1995,
     "value":"13215.555"
    },
    {
     "year":1996,
     "value":"13389.506"
    },
    {
     "year":1997,
     "value":"13235.392"
    },
    {
     "year":1998,
     "value":"13093.437"
    },
    {
     "year":1999,
     "value":"13162.097"
    },
    {
     "year":2000,
     "value":"13449.322"
    },
    {
     "year":2001,
     "value":"13696.734"
    },
    {
     "year":2002,
     "value":"14169.609"
    },
    {
     "year":2003,
     "value":"15330.279"
    },
    {
     "year":2004,
     "value":"16742.424"
    },
    {
     "year":2005,
     "value":"17860.367"
    },
    {
     "year":2006,
     "value":"18950.035"
    },
    {
     "year":2007,
     "value":"19891.314"
    },
    {
     "year":2008,
     "value":"20354.562"
    },
    {
     "year":2009,
     "value":"20451.994"
    },
    {
     "year":2010,
     "value":"21538.539"
    },
    {
     "year":2011,
     "value":"22684.719"
    },
    {
     "year":2012,
     "value":"23247.303"
    },
    {
     "year":2013,
     "value":"23580.283"
    },
    {
     "year":2014,
     "value":"23889.582"
    },
    {
     "year":2015,
     "value":"23863.449"
    },
    {
     "year":2016,
     "value":"24115.652"
    },
    {
     "year":2017,
     "value":"24579.148"
    },
    {
     "year":2018,
     "value":"25242.178"
    },
    {
     "year":2019,
     "value":"25684.332"
    },
    {
     "year":2020,
     "value":"25365.109"
    },
    {
     "year":2021,
     "value":"26958.795"
    }
   ]
  },
  {
   "indicator":"Expenditure on tertiary education (% of government expenditure on education)",
   "yearlyData":[
    {
     "year":2004,
     "value":"18.304170000000006"
    },
    {
     "year":2006,
     "value":"17.28856"
    },
    {
     "year":2007,
     "value":"18.47466"
    },
    {
     "year":2008,
     "value":"15.811055"
    },
    {
     "year":2009,
     "value":"19.152155"
    },
    {
     "year":2010,
     "value":"18.196975"
    },
    {
     "year":2011,
     "value":"17.77993"
    },
    {
     "year":2012,
     "value":"18.05857"
    },
    {
     "year":2016,
     "value":"18.663775"
    }
   ]
  },
  {
   "indicator":"Labor Force Participation Rate (%), Female",
   "yearlyData":[
    {
     "year":1990,
     "value":"62.9009226914052"
    },
    {
     "year":1991,
     "value":"62.717237967951895"
    },
    {
     "year":1992,
     "value":"62.5500225372474"
    },
    {
     "year":1993,
     "value":"62.1626034689129"
    },
    {
     "year":1994,
     "value":"62.069841785688496"
    },
    {
     "year":1995,
     "value":"62.0327062909803"
    },
    {
     "year":1996,
     "value":"61.7502429067396"
    },
    {
     "year":1997,
     "value":"61.6901290682746"
    },
    {
     "year":1998,
     "value":"61.5072105712417"
    },
    {
     "year":1999,
     "value":"61.6608009329643"
    },
    {
     "year":2000,
     "value":"61.450693995159995"
    },
    {
     "year":2001,
     "value":"61.0985669441041"
    },
    {
     "year":2002,
     "value":"60.9027145719561"
    },
    {
     "year":2003,
     "value":"60.5398777687924"
    },
    {
     "year":2004,
     "value":"60.234977948361795"
    },
    {
     "year":2005,
     "value":"60.005667733431395"
    },
    {
     "year":2006,
     "value":"59.619075458130595"
    },
    {
     "year":2007,
     "value":"59.2603501517476"
    },
    {
     "year":2008,
     "value":"58.8007768010042"
    },
    {
     "year":2009,
     "value":"58.463331224676"
    },
    {
     "year":2010,
     "value":"57.8017602484162"
    },
    {
     "year":2011,
     "value":"57.87150023466349"
    },
    {
     "year":2012,
     "value":"57.80033616618101"
    },
    {
     "year":2013,
     "value":"57.49526177520779"
    },
    {
     "year":2014,
     "value":"57.2623703034229"
    },
    {
     "year":2015,
     "value":"57.244118127113"
    },
    {
     "year":2016,
     "value":"57.1032240501447"
    },
    {
     "year":2017,
     "value":"56.9399862979985"
    },
    {
     "year":2018,
     "value":"56.8039318558125"
    },
    {
     "year":2019,
     "value":"56.738379489894896"
    },
    {
     "year":2020,
     "value":"54.0908432318693"
    },
    {
     "year":2021,
     "value":"56.047256834028"
    },
    {
     "year":2022,
     "value":"56.2626603025118"
    }
   ]
  },
  {
   "indicator":"Financial institution account (% age 15+)",
   "yearlyData":[
    {
     "year":2011,
     "value":"0.5655615925788879"
    },
    {
     "year":2014,
     "value":"0.7085665464401245"
    },
    {
     "year":2017,
     "value":"0.7206069231033325"
    },
    {
     "year":2021,
     "value":"0.8375169038772583"
    }
   ]
  },
  {
   "indicator":"Forest area (% of land area)",
   "yearlyData":[
    {
     "year":1990,
     "value":"36.79285341146029"
    },
    {
     "year":1991,
     "value":"36.69665629239101"
    },
    {
     "year":1992,
     "value":"38.43695922711258"
    },
    {
     "year":1993,
     "value":"38.38081088921504"
    },
    {
     "year":1994,
     "value":"38.325481984320156"
    },
    {
     "year":1995,
     "value":"38.2687798999042"
    },
    {
     "year":1996,
     "value":"38.21024915541994"
    },
    {
     "year":1997,
     "value":"38.150910324460966"
    },
    {
     "year":1998,
     "value":"38.110687490274415"
    },
    {
     "year":1999,
     "value":"38.046928096251406"
    },
    {
     "year":2000,
     "value":"37.99326544015895"
    },
    {
     "year":2001,
     "value":"37.95216389114693"
    },
    {
     "year":2002,
     "value":"37.912081809477954"
    },
    {
     "year":2003,
     "value":"37.870298506166115"
    },
    {
     "year":2004,
     "value":"37.82835277301514"
    },
    {
     "year":2005,
     "value":"37.786537925845366"
    },
    {
     "year":2006,
     "value":"37.73889230580061"
    },
    {
     "year":2007,
     "value":"37.69822399264661"
    },
    {
     "year":2008,
     "value":"37.658014629901686"
    },
    {
     "year":2009,
     "value":"37.619010569940144"
    },
    {
     "year":2010,
     "value":"37.578183962842225"
    },
    {
     "year":2011,
     "value":"37.56536677238193"
    },
    {
     "year":2012,
     "value":"37.55300682587979"
    },
    {
     "year":2013,
     "value":"37.542322142344425"
    },
    {
     "year":2014,
     "value":"37.529902241891605"
    },
    {
     "year":2015,
     "value":"37.51733006675223"
    },
    {
     "year":2016,
     "value":"37.50806773447531"
    },
    {
     "year":2017,
     "value":"37.486722498364394"
    },
    {
     "year":2018,
     "value":"37.48269665953881"
    },
    {
     "year":2019,
     "value":"37.474362093117854"
    },
    {
     "year":2020,
     "value":"37.46745498410528"
    }
   ]
  },
  {
   "indicator":"GDP per capita, PPP (current international $)",
   "yearlyData":[
    {
     "year":1990,
     "value":"3267.87110059953"
    },
    {
     "year":1991,
     "value":"3396.30081949336"
    },
    {
     "year":1992,
     "value":"3483.3432779261493"
    },
    {
     "year":1993,
     "value":"3656.9277421503707"
    },
    {
     "year":1994,
     "value":"3822.1709253912404"
    },
    {
     "year":1995,
     "value":"4006.04479316382"
    },
    {
     "year":1996,
     "value":"4244.35396382051"
    },
    {
     "year":1997,
     "value":"4515.87441671993"
    },
    {
     "year":1998,
     "value":"4565.23697058148"
    },
    {
     "year":1999,
     "value":"4758.2698053913"
    },
    {
     "year":2000,
     "value":"5156.18156236327"
    },
    {
     "year":2001,
     "value":"5420.52674011933"
    },
    {
     "year":2002,
     "value":"5723.85177519874"
    },
    {
     "year":2003,
     "value":"6138.468489964611"
    },
    {
     "year":2004,
     "value":"6783.16269273459"
    },
    {
     "year":2005,
     "value":"7508.27505663452"
    },
    {
     "year":2006,
     "value":"8507.542191632829"
    },
    {
     "year":2007,
     "value":"9511.15697825764"
    },
    {
     "year":2008,
     "value":"10436.8887458066"
    },
    {
     "year":2009,
     "value":"10739.714896421701"
    },
    {
     "year":2010,
     "value":"11697.956598943301"
    },
    {
     "year":2011,
     "value":"12739.9225143726"
    },
    {
     "year":2012,
     "value":"13561.4757009029"
    },
    {
     "year":2013,
     "value":"14287.680786741399"
    },
    {
     "year":2014,
     "value":"14757.224184991299"
    },
    {
     "year":2015,
     "value":"14826.582381381799"
    },
    {
     "year":2016,
     "value":"15279.804649423999"
    },
    {
     "year":2017,
     "value":"16094.077361788899"
    },
    {
     "year":2018,
     "value":"17186.8835768264"
    },
    {
     "year":2019,
     "value":"18031.460963218502"
    },
    {
     "year":2020,
     "value":"17970.3759021942"
    },
    {
     "year":2021,
     "value":"19926.0433444659"
    }
   ]
  },
  {
   "indicator":"International migrant stock at mid-year (both sexes)",
   "yearlyData":[
    {
     "year":1990,
     "value":"35289343.0"
    },
    {
     "year":1995,
     "value":"35213683.0"
    },
    {
     "year":2000,
     "value":"35822210.0"
    },
    {
     "year":2005,
     "value":"38209661.0"
    },
    {
     "year":2010,
     "value":"42080101.0"
    },
    {
     "year":2015,
     "value":"50991477.0"
    },
    {
     "year":2020,
     "value":"57383443.0"
    }
   ]
  },
  {
   "indicator":"Literacy Rate Female (%)",
   "yearlyData":[
    {
     "year":1980,
     "value":"62.675628662109396"
    },
    {
     "year":1981,
     "value":"63.66423034667971"
    },
    {
     "year":1982,
     "value":"64.4553985595703"
    },
    {
     "year":1983,
     "value":"65.7129592895508"
    },
    {
     "year":1984,
     "value":"66.924186706543"
    },
    {
     "year":1985,
     "value":"67.93197631835939"
    },
    {
     "year":1986,
     "value":"68.9089508056641"
    },
    {
     "year":1987,
     "value":"69.8312225341797"
    },
    {
     "year":1988,
     "value":"74.5746612548828"
    },
    {
     "year":1989,
     "value":"75.3131790161133"
    },
    {
     "year":1990,
     "value":"75.4225387573242"
    },
    {
     "year":1991,
     "value":"76.671272277832"
    },
    {
     "year":1992,
     "value":"77.3576965332031"
    },
    {
     "year":1993,
     "value":"78.02696228027341"
    },
    {
     "year":1994,
     "value":"78.6572494506836"
    },
    {
     "year":1995,
     "value":"79.29945373535159"
    },
    {
     "year":1996,
     "value":"79.9148406982422"
    },
    {
     "year":1997,
     "value":"86.5833892822266"
    },
    {
     "year":1998,
     "value":"87.1011505126953"
    },
    {
     "year":1999,
     "value":"87.53146362304692"
    },
    {
     "year":2000,
     "value":"87.8257904052734"
    },
    {
     "year":2001,
     "value":"88.3206329345703"
    },
    {
     "year":2002,
     "value":"88.72286987304692"
    },
    {
     "year":2003,
     "value":"89.2555999755859"
    },
    {
     "year":2004,
     "value":"89.6119766235352"
    },
    {
     "year":2005,
     "value":"90.08434295654301"
    },
    {
     "year":2006,
     "value":"90.3230514526367"
    },
    {
     "year":2007,
     "value":"91.6943893432617"
    },
    {
     "year":2008,
     "value":"92.0113067626953"
    },
    {
     "year":2009,
     "value":"92.2897186279297"
    },
    {
     "year":2010,
     "value":"92.41876220703129"
    },
    {
     "year":2011,
     "value":"92.9708786010742"
    },
    {
     "year":2012,
     "value":"93.52053833007808"
    },
    {
     "year":2013,
     "value":"93.5286407470703"
    },
    {
     "year":2014,
     "value":"93.8982391357422"
    },
    {
     "year":2015,
     "value":"93.7088775634766"
    },
    {
     "year":2016,
     "value":"94.3612213134766"
    },
    {
     "year":2017,
     "value":"94.3865814208984"
    },
    {
     "year":2018,
     "value":"94.1829376220703"
    },
    {
     "year":2019,
     "value":"94.58348846435551"
    },
    {
     "year":2020,
     "value":"94.71971893310551"
    }
   ]
  },
  {
   "indicator":"Literacy Rate Male (%)",
   "yearlyData":[
    {
     "year":1980,
     "value":"81.9933395385742"
    },
    {
     "year":1981,
     "value":"82.5737075805664"
    },
    {
     "year":1982,
     "value":"83.03330993652341"
    },
    {
     "year":1983,
     "value":"83.7140579223633"
    },
    {
     "year":1984,
     "value":"84.3402404785156"
    },
    {
     "year":1985,
     "value":"84.879768371582"
    },
    {
     "year":1986,
     "value":"85.3863830566406"
    },
    {
     "year":1987,
     "value":"85.8954391479492"
    },
    {
     "year":1988,
     "value":"88.3063507080078"
    },
    {
     "year":1989,
     "value":"88.657958984375"
    },
    {
     "year":1990,
     "value":"88.3942718505859"
    },
    {
     "year":1991,
     "value":"89.3220977783203"
    },
    {
     "year":1992,
     "value":"89.6948013305664"
    },
    {
     "year":1993,
     "value":"90.0541305541992"
    },
    {
     "year":1994,
     "value":"90.37548065185551"
    },
    {
     "year":1995,
     "value":"90.69528198242192"
    },
    {
     "year":1996,
     "value":"90.9869003295898"
    },
    {
     "year":1997,
     "value":"93.72911834716801"
    },
    {
     "year":1998,
     "value":"93.9383773803711"
    },
    {
     "year":1999,
     "value":"94.1328582763672"
    },
    {
     "year":2000,
     "value":"94.31896209716801"
    },
    {
     "year":2001,
     "value":"94.5442123413086"
    },
    {
     "year":2002,
     "value":"94.6885528564453"
    },
    {
     "year":2003,
     "value":"94.9906463623047"
    },
    {
     "year":2004,
     "value":"95.1567001342773"
    },
    {
     "year":2005,
     "value":"95.4001693725586"
    },
    {
     "year":2006,
     "value":"95.5319976806641"
    },
    {
     "year":2007,
     "value":"96.0831527709961"
    },
    {
     "year":2008,
     "value":"96.2332305908203"
    },
    {
     "year":2009,
     "value":"96.13436889648442"
    },
    {
     "year":2010,
     "value":"96.117919921875"
    },
    {
     "year":2011,
     "value":"96.4185409545898"
    },
    {
     "year":2012,
     "value":"96.8336868286133"
    },
    {
     "year":2013,
     "value":"96.8186416625977"
    },
    {
     "year":2014,
     "value":"97.03565216064449"
    },
    {
     "year":2015,
     "value":"96.7339630126953"
    },
    {
     "year":2016,
     "value":"97.2711715698242"
    },
    {
     "year":2017,
     "value":"97.18118286132808"
    },
    {
     "year":2018,
     "value":"96.8479537963867"
    },
    {
     "year":2019,
     "value":"97.1341171264648"
    },
    {
     "year":2020,
     "value":"97.1762008666992"
    }
   ]
  },
  {
   "indicator":"Labor Force Participation Rate (%), Male",
   "yearlyData":[
    {
     "year":1990,
     "value":"86.28169811110729"
    },
    {
     "year":1991,
     "value":"86.2117702006287"
    },
    {
     "year":1992,
     "value":"86.07608997966659"
    },
    {
     "year":1993,
     "value":"85.8083986656083"
    },
    {
     "year":1994,
     "value":"85.5499182285146"
    },
    {
     "year":1995,
     "value":"85.3232451543576"
    },
    {
     "year":1996,
     "value":"84.9588506177615"
    },
    {
     "year":1997,
     "value":"84.817272581756"
    },
    {
     "year":1998,
     "value":"84.5870137068987"
    },
    {
     "year":1999,
     "value":"84.6081253347099"
    },
    {
     "year":2000,
     "value":"84.3433838213653"
    },
    {
     "year":2001,
     "value":"83.9643769654628"
    },
    {
     "year":2002,
     "value":"83.6588500828176"
    },
    {
     "year":2003,
     "value":"83.3414131066289"
    },
    {
     "year":2004,
     "value":"83.1785590342842"
    },
    {
     "year":2005,
     "value":"82.9587076091636"
    },
    {
     "year":2006,
     "value":"82.6612486463642"
    },
    {
     "year":2007,
     "value":"82.452229158921"
    },
    {
     "year":2008,
     "value":"82.22195100993609"
    },
    {
     "year":2009,
     "value":"81.88372665547391"
    },
    {
     "year":2010,
     "value":"81.4415374197697"
    },
    {
     "year":2011,
     "value":"81.4846953778258"
    },
    {
     "year":2012,
     "value":"81.3346692857333"
    },
    {
     "year":2013,
     "value":"81.0113780930522"
    },
    {
     "year":2014,
     "value":"80.8654490940687"
    },
    {
     "year":2015,
     "value":"80.75344074299021"
    },
    {
     "year":2016,
     "value":"80.539434708362"
    },
    {
     "year":2017,
     "value":"80.31269084075029"
    },
    {
     "year":2018,
     "value":"80.08152638477121"
    },
    {
     "year":2019,
     "value":"79.8456590956996"
    },
    {
     "year":2020,
     "value":"77.2558991443153"
    },
    {
     "year":2021,
     "value":"79.5097868051306"
    }
   ]
  },
  {
   "indicator":"Ores and metals exports (% of merchandise exports)",
   "yearlyData":[
    {
     "year":1984,
     "value":"3.5687166082009982"
    },
    {
     "year":1985,
     "value":"3.151091712406948"
    },
    {
     "year":1986,
     "value":"3.0146095559749964"
    },
    {
     "year":1987,
     "value":"4.060778702721998"
    },
    {
     "year":1992,
     "value":"3.002290586245032"
    },
    {
     "year":1993,
     "value":"2.703933797713995"
    },
    {
     "year":1994,
     "value":"2.7714123983074885"
    },
    {
     "year":1995,
     "value":"3.3367503187840035"
    },
    {
     "year":1996,
     "value":"3.6184876049261434"
    },
    {
     "year":1997,
     "value":"3.8851092482496647"
    },
    {
     "year":1998,
     "value":"4.2781215338274"
    },
    {
     "year":1999,
     "value":"4.032252454732371"
    },
    {
     "year":2000,
     "value":"3.3525763710265917"
    },
    {
     "year":2001,
     "value":"3.4488101981204267"
    },
    {
     "year":2002,
     "value":"3.056119229892225"
    },
    {
     "year":2003,
     "value":"3.1475332838391066"
    },
    {
     "year":2004,
     "value":"3.618311649339968"
    },
    {
     "year":2005,
     "value":"3.6816595270013375"
    },
    {
     "year":2006,
     "value":"4.30907851851235"
    },
    {
     "year":2007,
     "value":"4.20719943901073"
    },
    {
     "year":2008,
     "value":"3.7967990749911023"
    },
    {
     "year":2009,
     "value":"3.3616320555440966"
    },
    {
     "year":2010,
     "value":"3.910892972686837"
    },
    {
     "year":2011,
     "value":"4.118805343900702"
    },
    {
     "year":2012,
     "value":"3.7447235037655"
    },
    {
     "year":2013,
     "value":"3.7035379137491966"
    },
    {
     "year":2014,
     "value":"3.502744490663856"
    },
    {
     "year":2015,
     "value":"3.4476988220972764"
    },
    {
     "year":2016,
     "value":"3.4333925557590548"
    },
    {
     "year":2017,
     "value":"3.662840495662613"
    },
    {
     "year":2018,
     "value":"3.654409975941169"
    },
    {
     "year":2019,
     "value":"3.7494856097416553"
    },
    {
     "year":2020,
     "value":"4.153082389917612"
    },
    {
     "year":2021,
     "value":"4.458353670050934"
    },
    {
     "year":2022,
     "value":"3.326617795572412"
    }
   ]
  },
  {
   "indicator":"Population ages 65 and above (% of total population)",
   "yearlyData":[
    {
     "year":1980,
     "value":"4.95415725361989"
    },
    {
     "year":1981,
     "value":"5.00265605513535"
    },
    {
     "year":1982,
     "value":"5.03449142363371"
    },
    {
     "year":1983,
     "value":"5.06870339969399"
    },
    {
     "year":1984,
     "value":"5.11185633638137"
    },
    {
     "year":1985,
     "value":"5.15837808931316"
    },
    {
     "year":1986,
     "value":"5.20963184492551"
    },
    {
     "year":1987,
     "value":"5.26404217014287"
    },
    {
     "year":1988,
     "value":"5.33265856214986"
    },
    {
     "year":1989,
     "value":"5.427035847144199"
    },
    {
     "year":1990,
     "value":"5.53102135978459"
    },
    {
     "year":1991,
     "value":"5.63822773102332"
    },
    {
     "year":1992,
     "value":"5.7645400211560895"
    },
    {
     "year":1993,
     "value":"5.911153802164298"
    },
    {
     "year":1994,
     "value":"6.05713444940787"
    },
    {
     "year":1995,
     "value":"6.2001287521598485"
    },
    {
     "year":1996,
     "value":"6.3375084434153"
    },
    {
     "year":1997,
     "value":"6.4723229769900295"
    },
    {
     "year":1998,
     "value":"6.61899798708116"
    },
    {
     "year":1999,
     "value":"6.76582864137602"
    },
    {
     "year":2000,
     "value":"6.913881592949622"
    },
    {
     "year":2001,
     "value":"7.07292928931762"
    },
    {
     "year":2002,
     "value":"7.240676416016838"
    },
    {
     "year":2003,
     "value":"7.4089394344162205"
    },
    {
     "year":2004,
     "value":"7.56557089461516"
    },
    {
     "year":2005,
     "value":"7.714979305565982"
    },
    {
     "year":2006,
     "value":"7.86337753137229"
    },
    {
     "year":2007,
     "value":"7.98948253569661"
    },
    {
     "year":2008,
     "value":"8.08360925301082"
    },
    {
     "year":2009,
     "value":"8.172764918600969"
    },
    {
     "year":2010,
     "value":"8.28079901402692"
    },
    {
     "year":2011,
     "value":"8.43128925302457"
    },
    {
     "year":2012,
     "value":"8.62278049013364"
    },
    {
     "year":2013,
     "value":"8.84355890181169"
    },
    {
     "year":2014,
     "value":"9.09966798192697"
    },
    {
     "year":2015,
     "value":"9.405209103401221"
    },
    {
     "year":2016,
     "value":"9.741298653935141"
    },
    {
     "year":2017,
     "value":"10.1125203077039"
    },
    {
     "year":2018,
     "value":"10.5150386367577"
    },
    {
     "year":2019,
     "value":"10.928015356531803"
    },
    {
     "year":2020,
     "value":"11.3513521533727"
    },
    {
     "year":2021,
     "value":"11.7424163263176"
    }
   ]
  },
  {
   "indicator":"Population using at least basic drinking-water services (%)",
   "yearlyData":[
    {
     "year":2000,
     "value":"85.0810848072427"
    },
    {
     "year":2001,
     "value":"85.4217195626239"
    },
    {
     "year":2002,
     "value":"86.1440320023798"
    },
    {
     "year":2003,
     "value":"86.8514948857701"
    },
    {
     "year":2004,
     "value":"87.54117581882143"
    },
    {
     "year":2005,
     "value":"88.2138137976367"
    },
    {
     "year":2006,
     "value":"88.8669603970099"
    },
    {
     "year":2007,
     "value":"89.49828517639929"
    },
    {
     "year":2008,
     "value":"90.1079878339576"
    },
    {
     "year":2009,
     "value":"90.6919586538808"
    },
    {
     "year":2010,
     "value":"91.2568967967092"
    },
    {
     "year":2011,
     "value":"91.7962420525235"
    },
    {
     "year":2012,
     "value":"92.31232220286293"
    },
    {
     "year":2013,
     "value":"92.8094625476483"
    },
    {
     "year":2014,
     "value":"93.29018561801821"
    },
    {
     "year":2015,
     "value":"93.7531124650238"
    },
    {
     "year":2016,
     "value":"94.18634553397553"
    },
    {
     "year":2017,
     "value":"94.55075330758312"
    },
    {
     "year":2018,
     "value":"94.96590869006651"
    },
    {
     "year":2019,
     "value":"95.3420738326396"
    },
    {
     "year":2020,
     "value":"95.70225935867269"
    }
   ]
  },
  {
   "indicator":"Population using at least basic drinking-water services (%)::Rural",
   "yearlyData":[
    {
     "year":2000,
     "value":"72.64898724179271"
    },
    {
     "year":2001,
     "value":"72.82352416817241"
    },
    {
     "year":2002,
     "value":"73.7865964693351"
    },
    {
     "year":2003,
     "value":"74.74953099570841"
    },
    {
     "year":2004,
     "value":"75.7115121466625"
    },
    {
     "year":2005,
     "value":"76.6721745247428"
    },
    {
     "year":2006,
     "value":"77.63924329786329"
    },
    {
     "year":2007,
     "value":"78.60365944446059"
    },
    {
     "year":2008,
     "value":"79.5614559210647"
    },
    {
     "year":2009,
     "value":"80.5057297250474"
    },
    {
     "year":2010,
     "value":"81.4492117327632"
    },
    {
     "year":2011,
     "value":"82.39424831794929"
    },
    {
     "year":2012,
     "value":"83.3361149880727"
    },
    {
     "year":2013,
     "value":"84.2720919620882"
    },
    {
     "year":2014,
     "value":"85.2090964219344"
    },
    {
     "year":2015,
     "value":"86.1442147273743"
    },
    {
     "year":2016,
     "value":"87.0454873129624"
    },
    {
     "year":2017,
     "value":"87.98011792862341"
    },
    {
     "year":2018,
     "value":"88.90617770609819"
    },
    {
     "year":2019,
     "value":"89.85567537822229"
    },
    {
     "year":2020,
     "value":"90.84393685729141"
    }
   ]
  },
  {
   "indicator":"Population using at least basic drinking-water services (%)::Urban",
   "yearlyData":[
    {
     "year":2000,
     "value":"97.69060703273131"
    },
    {
     "year":2001,
     "value":"97.7533605550758"
    },
    {
     "year":2002,
     "value":"97.7880722702919"
    },
    {
     "year":2003,
     "value":"97.82151019360201"
    },
    {
     "year":2004,
     "value":"97.85136807009808"
    },
    {
     "year":2005,
     "value":"97.88176343087619"
    },
    {
     "year":2006,
     "value":"97.91105932447522"
    },
    {
     "year":2007,
     "value":"97.93988249479341"
    },
    {
     "year":2008,
     "value":"97.96579613183079"
    },
    {
     "year":2009,
     "value":"97.98776864673307"
    },
    {
     "year":2010,
     "value":"98.00821414920472"
    },
    {
     "year":2011,
     "value":"98.0276124288677"
    },
    {
     "year":2012,
     "value":"98.04573781895408"
    },
    {
     "year":2013,
     "value":"98.0627645723558"
    },
    {
     "year":2014,
     "value":"98.07785755719652"
    },
    {
     "year":2015,
     "value":"98.09292354981709"
    },
    {
     "year":2016,
     "value":"98.10713222591872"
    },
    {
     "year":2017,
     "value":"98.136826086153"
    },
    {
     "year":2018,
     "value":"98.1544537199997"
    },
    {
     "year":2019,
     "value":"98.1309008527436"
    },
    {
     "year":2020,
     "value":"98.0914168500703"
    }
   ]
  },
  {
   "indicator":"Population using at least basic sanitation services (%)",
   "yearlyData":[
    {
     "year":2000,
     "value":"66.2399069180338"
    },
    {
     "year":2001,
     "value":"66.9088672858372"
    },
    {
     "year":2002,
     "value":"68.4106872163913"
    },
    {
     "year":2003,
     "value":"69.8976393513824"
    },
    {
     "year":2004,
     "value":"71.3692443498528"
    },
    {
     "year":2005,
     "value":"72.8411887224552"
    },
    {
     "year":2006,
     "value":"74.2935518401401"
    },
    {
     "year":2007,
     "value":"75.7179916369279"
    },
    {
     "year":2008,
     "value":"77.12054636307201"
    },
    {
     "year":2009,
     "value":"78.5020458561295"
    },
    {
     "year":2010,
     "value":"79.859936247281"
    },
    {
     "year":2011,
     "value":"81.18806280528742"
    },
    {
     "year":2012,
     "value":"82.49118326295459"
    },
    {
     "year":2013,
     "value":"83.77853391200401"
    },
    {
     "year":2014,
     "value":"85.0450784926377"
    },
    {
     "year":2015,
     "value":"86.2828548548338"
    },
    {
     "year":2016,
     "value":"87.4925461579703"
    },
    {
     "year":2017,
     "value":"88.5473469415072"
    },
    {
     "year":2018,
     "value":"89.72597371767709"
    },
    {
     "year":2019,
     "value":"90.7337856932708"
    },
    {
     "year":2020,
     "value":"91.83193806518592"
    }
   ]
  },
  {
   "indicator":"Poverty headcount ratio at $2.15 a day (2017 PPP) (% of population)",
   "yearlyData":[
    {
     "year":1981,
     "value":"59.2"
    },
    {
     "year":1982,
     "value":"58.0"
    },
    {
     "year":1983,
     "value":"56.7"
    },
    {
     "year":1984,
     "value":"53.3"
    },
    {
     "year":1985,
     "value":"49.9"
    },
    {
     "year":1986,
     "value":"46.6"
    },
    {
     "year":1987,
     "value":"44.2"
    },
    {
     "year":1988,
     "value":"40.4"
    },
    {
     "year":1989,
     "value":"47.9"
    },
    {
     "year":1990,
     "value":"47.1"
    },
    {
     "year":1991,
     "value":"45.9"
    },
    {
     "year":1992,
     "value":"43.9"
    },
    {
     "year":1993,
     "value":"41.8"
    },
    {
     "year":1994,
     "value":"38.4"
    },
    {
     "year":1995,
     "value":"36.0"
    },
    {
     "year":1996,
     "value":"33.2"
    },
    {
     "year":1997,
     "value":"32.6"
    },
    {
     "year":1998,
     "value":"32.1"
    },
    {
     "year":1999,
     "value":"31.7"
    },
    {
     "year":2000,
     "value":"28.9"
    },
    {
     "year":2001,
     "value":"27.3"
    },
    {
     "year":2002,
     "value":"25.0"
    },
    {
     "year":2003,
     "value":"22.6"
    },
    {
     "year":2004,
     "value":"19.4"
    },
    {
     "year":2005,
     "value":"15.8"
    },
    {
     "year":2006,
     "value":"14.5"
    },
    {
     "year":2007,
     "value":"13.2"
    },
    {
     "year":2008,
     "value":"12.4"
    },
    {
     "year":2009,
     "value":"11.2"
    },
    {
     "year":2010,
     "value":"9.8"
    },
    {
     "year":2011,
     "value":"7.5"
    },
    {
     "year":2012,
     "value":"6.4"
    },
    {
     "year":2013,
     "value":"3.0"
    },
    {
     "year":2014,
     "value":"2.5"
    },
    {
     "year":2015,
     "value":"2.0"
    },
    {
     "year":2016,
     "value":"1.9"
    },
    {
     "year":2017,
     "value":"1.8"
    },
    {
     "year":2018,
     "value":"1.6"
    },
    {
     "year":2019,
     "value":"1.5"
    }
   ]
  },
  {
   "indicator":"Poverty headcount ratio at $3.65 a day (2017 PPP) (% of population)",
   "yearlyData":[
    {
     "year":1981,
     "value":"69.3"
    },
    {
     "year":1982,
     "value":"69.3"
    },
    {
     "year":1983,
     "value":"69.7"
    },
    {
     "year":1984,
     "value":"68.8"
    },
    {
     "year":1985,
     "value":"67.6"
    },
    {
     "year":1986,
     "value":"65.4"
    },
    {
     "year":1987,
     "value":"65.0"
    },
    {
     "year":1988,
     "value":"63.5"
    },
    {
     "year":1989,
     "value":"64.9"
    },
    {
     "year":1990,
     "value":"64.8"
    },
    {
     "year":1991,
     "value":"64.7"
    },
    {
     "year":1992,
     "value":"63.7"
    },
    {
     "year":1993,
     "value":"62.2"
    },
    {
     "year":1994,
     "value":"60.1"
    },
    {
     "year":1995,
     "value":"58.2"
    },
    {
     "year":1996,
     "value":"56.4"
    },
    {
     "year":1997,
     "value":"55.1"
    },
    {
     "year":1998,
     "value":"54.1"
    },
    {
     "year":1999,
     "value":"53.6"
    },
    {
     "year":2000,
     "value":"50.3"
    },
    {
     "year":2001,
     "value":"48.3"
    },
    {
     "year":2002,
     "value":"45.4"
    },
    {
     "year":2003,
     "value":"43.3"
    },
    {
     "year":2004,
     "value":"39.8"
    },
    {
     "year":2005,
     "value":"35.7"
    },
    {
     "year":2006,
     "value":"32.9"
    },
    {
     "year":2007,
     "value":"30.1"
    },
    {
     "year":2008,
     "value":"28.2"
    },
    {
     "year":2009,
     "value":"26.2"
    },
    {
     "year":2010,
     "value":"23.7"
    },
    {
     "year":2011,
     "value":"20.3"
    },
    {
     "year":2012,
     "value":"17.9"
    },
    {
     "year":2013,
     "value":"12.8"
    },
    {
     "year":2014,
     "value":"10.8"
    },
    {
     "year":2015,
     "value":"9.1"
    },
    {
     "year":2016,
     "value":"8.0"
    },
    {
     "year":2017,
     "value":"7.4"
    },
    {
     "year":2018,
     "value":"6.2"
    },
    {
     "year":2019,
     "value":"5.1"
    }
   ]
  },
  {
   "indicator":"Poverty headcount ratio at $6.85 a day (2017 PPP) (% of population)",
   "yearlyData":[
    {
     "year":1981,
     "value":"78.9"
    },
    {
     "year":1982,
     "value":"78.9"
    },
    {
     "year":1983,
     "value":"79.6"
    },
    {
     "year":1984,
     "value":"79.5"
    },
    {
     "year":1985,
     "value":"79.1"
    },
    {
     "year":1986,
     "value":"77.4"
    },
    {
     "year":1987,
     "value":"78.0"
    },
    {
     "year":1988,
     "value":"78.1"
    },
    {
     "year":1989,
     "value":"77.9"
    },
    {
     "year":1990,
     "value":"78.0"
    },
    {
     "year":1991,
     "value":"78.7"
    },
    {
     "year":1992,
     "value":"79.3"
    },
    {
     "year":1993,
     "value":"79.2"
    },
    {
     "year":1994,
     "value":"78.5"
    },
    {
     "year":1995,
     "value":"77.7"
    },
    {
     "year":1996,
     "value":"77.0"
    },
    {
     "year":1997,
     "value":"76.3"
    },
    {
     "year":1998,
     "value":"75.9"
    },
    {
     "year":1999,
     "value":"76.3"
    },
    {
     "year":2000,
     "value":"73.9"
    },
    {
     "year":2001,
     "value":"72.2"
    },
    {
     "year":2002,
     "value":"69.9"
    },
    {
     "year":2003,
     "value":"68.9"
    },
    {
     "year":2004,
     "value":"65.9"
    },
    {
     "year":2005,
     "value":"62.4"
    },
    {
     "year":2006,
     "value":"59.4"
    },
    {
     "year":2007,
     "value":"56.0"
    },
    {
     "year":2008,
     "value":"53.5"
    },
    {
     "year":2009,
     "value":"51.4"
    },
    {
     "year":2010,
     "value":"48.3"
    },
    {
     "year":2011,
     "value":"45.3"
    },
    {
     "year":2012,
     "value":"42.1"
    },
    {
     "year":2013,
     "value":"37.6"
    },
    {
     "year":2014,
     "value":"34.5"
    },
    {
     "year":2015,
     "value":"31.7"
    },
    {
     "year":2016,
     "value":"29.6"
    },
    {
     "year":2017,
     "value":"28.1"
    },
    {
     "year":2018,
     "value":"25.6"
    },
    {
     "year":2019,
     "value":"23.5"
    }
   ]
  },
  {
   "indicator":"CPIA Public sector management and institutions",
   "yearlyData":[
    {
     "year":2005,
     "value":"3.43571428571429"
    },
    {
     "year":2006,
     "value":"3.39285714285714"
    },
    {
     "year":2007,
     "value":"3.5"
    },
    {
     "year":2008,
     "value":"3.55"
    },
    {
     "year":2009,
     "value":"3.54615384615385"
    },
    {
     "year":2010,
     "value":"3.5615384615384604"
    },
    {
     "year":2011,
     "value":"3.5153846153846096"
    },
    {
     "year":2012,
     "value":"3.50714285714286"
    },
    {
     "year":2013,
     "value":"3.5"
    },
    {
     "year":2014,
     "value":"3.42727272727273"
    },
    {
     "year":2015,
     "value":"3.39090909090909"
    },
    {
     "year":2016,
     "value":"3.39090909090909"
    },
    {
     "year":2017,
     "value":"3.38181818181818"
    },
    {
     "year":2018,
     "value":"3.38181818181818"
    },
    {
     "year":2019,
     "value":"3.4"
    },
    {
     "year":2020,
     "value":"3.37272727272727"
    },
    {
     "year":2021,
     "value":"3.4"
    }
   ]
  },
  {
   "indicator":"Refugee population by country or territory of asylum",
   "yearlyData":[
    {
     "year":1990,
     "value":"2289261.0"
    },
    {
     "year":1991,
     "value":"2252038.0"
    },
    {
     "year":1992,
     "value":"3390333.0"
    },
    {
     "year":1993,
     "value":"3144420.0"
    },
    {
     "year":1994,
     "value":"3006009.0"
    },
    {
     "year":1995,
     "value":"3243177.0"
    },
    {
     "year":1996,
     "value":"3368323.0"
    },
    {
     "year":1997,
     "value":"3426325.0"
    },
    {
     "year":1998,
     "value":"3414442.0"
    },
    {
     "year":1999,
     "value":"3454983.0"
    },
    {
     "year":2000,
     "value":"3185143.0"
    },
    {
     "year":2001,
     "value":"3131517.0"
    },
    {
     "year":2002,
     "value":"3099423.0"
    },
    {
     "year":2003,
     "value":"2928191.0"
    },
    {
     "year":2004,
     "value":"2958736.0"
    },
    {
     "year":2005,
     "value":"2836882.0"
    },
    {
     "year":2006,
     "value":"3214730.0"
    },
    {
     "year":2007,
     "value":"3416041.0"
    },
    {
     "year":2008,
     "value":"3302835.0"
    },
    {
     "year":2009,
     "value":"3315487.0"
    },
    {
     "year":2010,
     "value":"3274560.0"
    },
    {
     "year":2011,
     "value":"3299718.0"
    },
    {
     "year":2012,
     "value":"3511294.0"
    },
    {
     "year":2013,
     "value":"4457930.0"
    },
    {
     "year":2014,
     "value":"5791070.0"
    },
    {
     "year":2015,
     "value":"6810777.0"
    },
    {
     "year":2016,
     "value":"7056650.0"
    },
    {
     "year":2017,
     "value":"7620499.0"
    },
    {
     "year":2018,
     "value":"7871490.0"
    },
    {
     "year":2019,
     "value":"7738682.0"
    },
    {
     "year":2020,
     "value":"7966067.0"
    },
    {
     "year":2021,
     "value":"8027851.0"
    }
   ]
  },
  {
   "indicator":"Remittance as % of GDP",
   "yearlyData":[
    {
     "year":1980,
     "value":"5092038218.2812"
    },
    {
     "year":1981,
     "value":"6119829607.7179"
    },
    {
     "year":1982,
     "value":"6382085512.1979"
    },
    {
     "year":1983,
     "value":"6026215820.7145"
    },
    {
     "year":1984,
     "value":"6554624865.0239"
    },
    {
     "year":1985,
     "value":"6252981242.4544"
    },
    {
     "year":1986,
     "value":"6886378494.0974"
    },
    {
     "year":1987,
     "value":"7432335650.3061"
    },
    {
     "year":1988,
     "value":"7741595253.9471"
    },
    {
     "year":1989,
     "value":"9274258388.5592"
    },
    {
     "year":1990,
     "value":"10500194405.3552"
    },
    {
     "year":1991,
     "value":"11116755267.148998"
    },
    {
     "year":1992,
     "value":"12874777321.606"
    },
    {
     "year":1993,
     "value":"14131233156.6766"
    },
    {
     "year":1994,
     "value":"21017825857.3842"
    },
    {
     "year":1995,
     "value":"19231734904.5283"
    },
    {
     "year":1996,
     "value":"21481462952.7104"
    },
    {
     "year":1997,
     "value":"25959572678.4451"
    },
    {
     "year":1998,
     "value":"26054726181.9075"
    },
    {
     "year":1999,
     "value":"27216595132.3319"
    },
    {
     "year":2000,
     "value":"29760054671.5761"
    },
    {
     "year":2001,
     "value":"33246770343.4123"
    },
    {
     "year":2002,
     "value":"37756379956.1935"
    },
    {
     "year":2003,
     "value":"48745879282.9808"
    },
    {
     "year":2004,
     "value":"59946986650.2567"
    },
    {
     "year":2005,
     "value":"65388422362.3006"
    },
    {
     "year":2006,
     "value":"76333064029.9517"
    },
    {
     "year":2007,
     "value":"90029227454.6116"
    },
    {
     "year":2008,
     "value":"96519715603.6215"
    },
    {
     "year":2009,
     "value":"89165926121.61699"
    },
    {
     "year":2010,
     "value":"95642354196.5501"
    },
    {
     "year":2011,
     "value":"104900840038.723"
    },
    {
     "year":2012,
     "value":"105569556608.416"
    },
    {
     "year":2013,
     "value":"112294049210.145"
    },
    {
     "year":2014,
     "value":"128736938129.905"
    },
    {
     "year":2015,
     "value":"129032558297.209"
    },
    {
     "year":2016,
     "value":"125228283069.651"
    },
    {
     "year":2017,
     "value":"138722722873.99402"
    },
    {
     "year":2018,
     "value":"145156525538.954"
    },
    {
     "year":2019,
     "value":"147329697731.53302"
    },
    {
     "year":2020,
     "value":"151625272707.999"
    },
    {
     "year":2021,
     "value":"182261709631.823"
    },
    {
     "year":2022,
     "value":"220882936152.155"
    }
   ]
  },
  {
   "indicator":"Renewable internal freshwater resources per capita (cubic meters)",
   "yearlyData":[
    {
     "year":1980,
     "value":"10729.00480010344"
    },
    {
     "year":1981,
     "value":"10560.27550462126"
    },
    {
     "year":1982,
     "value":"10381.780516728468"
    },
    {
     "year":1983,
     "value":"10207.580975449286"
    },
    {
     "year":1984,
     "value":"10045.796697850044"
    },
    {
     "year":1985,
     "value":"9885.140361436394"
    },
    {
     "year":1986,
     "value":"9719.553009211408"
    },
    {
     "year":1987,
     "value":"9549.738374784289"
    },
    {
     "year":1988,
     "value":"9383.74969817192"
    },
    {
     "year":1989,
     "value":"9226.483095229722"
    },
    {
     "year":1990,
     "value":"9078.410731708676"
    },
    {
     "year":1991,
     "value":"8941.049508192194"
    },
    {
     "year":1992,
     "value":"10199.201462530194"
    },
    {
     "year":1993,
     "value":"10075.183222399182"
    },
    {
     "year":1994,
     "value":"9954.67622680636"
    },
    {
     "year":1995,
     "value":"9840.715704820564"
    },
    {
     "year":1996,
     "value":"9730.95562085571"
    },
    {
     "year":1997,
     "value":"9626.252628542105"
    },
    {
     "year":1998,
     "value":"9527.181701034711"
    },
    {
     "year":1999,
     "value":"9436.118247704037"
    },
    {
     "year":2000,
     "value":"9351.861201217262"
    },
    {
     "year":2001,
     "value":"9273.218300970428"
    },
    {
     "year":2002,
     "value":"9199.37247157"
    },
    {
     "year":2003,
     "value":"9129.25801020644"
    },
    {
     "year":2004,
     "value":"9061.326507548838"
    },
    {
     "year":2005,
     "value":"8994.317650802006"
    },
    {
     "year":2006,
     "value":"8905.77555581993"
    },
    {
     "year":2007,
     "value":"8847.216367106928"
    },
    {
     "year":2008,
     "value":"8786.45539303905"
    },
    {
     "year":2009,
     "value":"8724.720767923647"
    },
    {
     "year":2010,
     "value":"8665.864737055508"
    },
    {
     "year":2011,
     "value":"8603.373181352414"
    },
    {
     "year":2012,
     "value":"8532.969634443429"
    },
    {
     "year":2013,
     "value":"8460.012310655791"
    },
    {
     "year":2014,
     "value":"8388.307820138341"
    },
    {
     "year":2015,
     "value":"8320.853484804169"
    },
    {
     "year":2016,
     "value":"8258.971694411279"
    },
    {
     "year":2017,
     "value":"8199.183161537547"
    },
    {
     "year":2018,
     "value":"8146.016036522232"
    },
    {
     "year":2019,
     "value":"8099.615115707974"
    },
    {
     "year":2020,
     "value":"8062.692771665445"
    }
   ]
  },
  {
   "indicator":"School enrollment, tertiary (% gross)",
   "yearlyData":[
    {
     "year":1980,
     "value":"8.994729995727539"
    },
    {
     "year":1981,
     "value":"9.19828033447266"
    },
    {
     "year":1982,
     "value":"9.49962997436523"
    },
    {
     "year":1983,
     "value":"9.49911975860596"
    },
    {
     "year":1984,
     "value":"9.91794013977051"
    },
    {
     "year":1985,
     "value":"10.1453895568848"
    },
    {
     "year":1986,
     "value":"9.90672969818115"
    },
    {
     "year":1987,
     "value":"9.86454963684082"
    },
    {
     "year":1988,
     "value":"9.68513011932373"
    },
    {
     "year":1989,
     "value":"9.57127952575684"
    },
    {
     "year":1990,
     "value":"9.56770992279053"
    },
    {
     "year":1991,
     "value":"9.629150390625"
    },
    {
     "year":1992,
     "value":"9.63553047180176"
    },
    {
     "year":1993,
     "value":"9.738200187683107"
    },
    {
     "year":1994,
     "value":"10.4184598922729"
    },
    {
     "year":1995,
     "value":"11.4529495239258"
    },
    {
     "year":1996,
     "value":"11.997710227966301"
    },
    {
     "year":1997,
     "value":"13.2948799133301"
    },
    {
     "year":1998,
     "value":"14.234210014343299"
    },
    {
     "year":1999,
     "value":"15.6371402740479"
    },
    {
     "year":2000,
     "value":"17.1098308563232"
    },
    {
     "year":2001,
     "value":"19.3383502960205"
    },
    {
     "year":2002,
     "value":"21.8551197052002"
    },
    {
     "year":2003,
     "value":"24.302860260009798"
    },
    {
     "year":2004,
     "value":"25.8236904144287"
    },
    {
     "year":2005,
     "value":"27.007299423217802"
    },
    {
     "year":2006,
     "value":"28.0906600952148"
    },
    {
     "year":2007,
     "value":"28.664739608764602"
    },
    {
     "year":2008,
     "value":"29.2826099395752"
    },
    {
     "year":2009,
     "value":"30.7113094329834"
    },
    {
     "year":2010,
     "value":"32.3204307556152"
    },
    {
     "year":2011,
     "value":"34.0963516235352"
    },
    {
     "year":2012,
     "value":"36.4893798828125"
    },
    {
     "year":2013,
     "value":"39.4165802001953"
    },
    {
     "year":2014,
     "value":"45.6454086303711"
    },
    {
     "year":2015,
     "value":"48.3436393737793"
    },
    {
     "year":2016,
     "value":"50.2740287780762"
    },
    {
     "year":2017,
     "value":"51.4999389648438"
    },
    {
     "year":2018,
     "value":"52.8473014831543"
    },
    {
     "year":2019,
     "value":"54.97436904907229"
    },
    {
     "year":2020,
     "value":"57.9957389831543"
    }
   ]
  },
  {
   "indicator":"CPIA policies for social inclusion\/equity cluster average",
   "yearlyData":[
    {
     "year":2005,
     "value":"3.68571428571429"
    },
    {
     "year":2006,
     "value":"3.678571428571431"
    },
    {
     "year":2007,
     "value":"3.75"
    },
    {
     "year":2008,
     "value":"3.78333333333333"
    },
    {
     "year":2009,
     "value":"3.73076923076923"
    },
    {
     "year":2010,
     "value":"3.73076923076923"
    },
    {
     "year":2011,
     "value":"3.61538461538462"
    },
    {
     "year":2012,
     "value":"3.55714285714286"
    },
    {
     "year":2013,
     "value":"3.55"
    },
    {
     "year":2014,
     "value":"3.41818181818182"
    },
    {
     "year":2015,
     "value":"3.39090909090909"
    },
    {
     "year":2016,
     "value":"3.37272727272727"
    },
    {
     "year":2017,
     "value":"3.35454545454545"
    },
    {
     "year":2018,
     "value":"3.38181818181818"
    },
    {
     "year":2019,
     "value":"3.4363636363636405"
    },
    {
     "year":2020,
     "value":"3.4363636363636405"
    },
    {
     "year":2021,
     "value":"3.4363636363636405"
    }
   ]
  },
  {
   "indicator":"Electricity generation from solar, measured in terawatt-hours",
   "yearlyData":[
    {
     "year":1980,
     "value":"0.0"
    },
    {
     "year":1981,
     "value":"0.0"
    },
    {
     "year":1982,
     "value":"0.0"
    },
    {
     "year":1983,
     "value":"0.0"
    },
    {
     "year":1984,
     "value":"0.0"
    },
    {
     "year":1985,
     "value":"0.0"
    },
    {
     "year":1986,
     "value":"0.0"
    },
    {
     "year":1987,
     "value":"0.0"
    },
    {
     "year":1988,
     "value":"0.0"
    },
    {
     "year":1989,
     "value":"0.0"
    },
    {
     "year":1990,
     "value":"0.003"
    },
    {
     "year":1991,
     "value":"0.004"
    },
    {
     "year":1992,
     "value":"0.006"
    },
    {
     "year":1993,
     "value":"0.008"
    },
    {
     "year":1994,
     "value":"0.01"
    },
    {
     "year":1995,
     "value":"0.012"
    },
    {
     "year":1996,
     "value":"0.015"
    },
    {
     "year":1997,
     "value":"0.017"
    },
    {
     "year":1998,
     "value":"0.021"
    },
    {
     "year":1999,
     "value":"0.024"
    },
    {
     "year":2000,
     "value":"0.04"
    },
    {
     "year":2001,
     "value":"0.05"
    },
    {
     "year":2002,
     "value":"0.09"
    },
    {
     "year":2003,
     "value":"0.1"
    },
    {
     "year":2004,
     "value":"0.12"
    },
    {
     "year":2005,
     "value":"0.12"
    },
    {
     "year":2006,
     "value":"0.13"
    },
    {
     "year":2007,
     "value":"0.15"
    },
    {
     "year":2008,
     "value":"0.19"
    },
    {
     "year":2009,
     "value":"0.33"
    },
    {
     "year":2010,
     "value":"0.81"
    },
    {
     "year":2011,
     "value":"2.89"
    },
    {
     "year":2012,
     "value":"5.14"
    },
    {
     "year":2013,
     "value":"12.23"
    },
    {
     "year":2014,
     "value":"30.69"
    },
    {
     "year":2015,
     "value":"49.78"
    },
    {
     "year":2016,
     "value":"80.25"
    },
    {
     "year":2017,
     "value":"137.81"
    },
    {
     "year":2018,
     "value":"207.33"
    },
    {
     "year":2019,
     "value":"269.14"
    },
    {
     "year":2020,
     "value":"321.24"
    },
    {
     "year":2021,
     "value":"401.84"
    }
   ]
  },
  {
   "indicator":"Strength of legal rights index (0=weak to 12=strong)",
   "yearlyData":[
    {
     "year":2013,
     "value":"4.88"
    },
    {
     "year":2014,
     "value":"5.1"
    },
    {
     "year":2015,
     "value":"5.36"
    },
    {
     "year":2016,
     "value":"5.46"
    },
    {
     "year":2017,
     "value":"5.78"
    },
    {
     "year":2018,
     "value":"5.96"
    },
    {
     "year":2019,
     "value":"6.3"
    }
   ]
  },
  {
   "indicator":"Tax revenue (Percent of GDP)",
   "yearlyData":[
    {
     "year":2005,
     "value":"10.6628441318315"
    },
    {
     "year":2006,
     "value":"11.0795869681253"
    },
    {
     "year":2007,
     "value":"11.6261238654865"
    },
    {
     "year":2008,
     "value":"12.029358628371199"
    },
    {
     "year":2009,
     "value":"11.694213472831096"
    },
    {
     "year":2010,
     "value":"12.0084249010656"
    },
    {
     "year":2011,
     "value":"12.313041464265599"
    },
    {
     "year":2012,
     "value":"12.1309994123278"
    },
    {
     "year":2013,
     "value":"11.959712396352598"
    },
    {
     "year":2014,
     "value":"11.686276404426"
    },
    {
     "year":2015,
     "value":"11.3997519049224"
    },
    {
     "year":2016,
     "value":"11.131775614168598"
    },
    {
     "year":2017,
     "value":"11.278820658529801"
    },
    {
     "year":2018,
     "value":"11.1726552062677"
    },
    {
     "year":2019,
     "value":"10.802638916995196"
    },
    {
     "year":2020,
     "value":"10.5934088139324"
    }
   ]
  },
  {
   "indicator":"Population, total",
   "yearlyData":[
    {
     "year":1980,
     "value":"1638933463.0"
    },
    {
     "year":1981,
     "value":"1665397690.0"
    },
    {
     "year":1982,
     "value":"1692566270.0"
    },
    {
     "year":1983,
     "value":"1722004862.0"
    },
    {
     "year":1984,
     "value":"1749207822.0"
    },
    {
     "year":1985,
     "value":"1777447252.0"
    },
    {
     "year":1986,
     "value":"1806703227.0"
    },
    {
     "year":1987,
     "value":"1838458331.0"
    },
    {
     "year":1988,
     "value":"1871391671.0"
    },
    {
     "year":1989,
     "value":"1902803566.0"
    },
    {
     "year":1990,
     "value":"1934109457.0"
    },
    {
     "year":1991,
     "value":"1965875201.0"
    },
    {
     "year":1992,
     "value":"1991248729.0"
    },
    {
     "year":1993,
     "value":"2014343813.0"
    },
    {
     "year":1994,
     "value":"2037189377.0"
    },
    {
     "year":1995,
     "value":"2058606574.0"
    },
    {
     "year":1996,
     "value":"2079356671.0"
    },
    {
     "year":1997,
     "value":"2099183238.0"
    },
    {
     "year":1998,
     "value":"2118174924.0"
    },
    {
     "year":1999,
     "value":"2136278003.0"
    },
    {
     "year":2000,
     "value":"2153877581.0"
    },
    {
     "year":2001,
     "value":"2172056530.0"
    },
    {
     "year":2002,
     "value":"2189386264.0"
    },
    {
     "year":2003,
     "value":"2206369384.0"
    },
    {
     "year":2004,
     "value":"2222786325.0"
    },
    {
     "year":2005,
     "value":"2239778347.0"
    },
    {
     "year":2006,
     "value":"2256546925.0"
    },
    {
     "year":2007,
     "value":"2272932027.0"
    },
    {
     "year":2008,
     "value":"2289517148.0"
    },
    {
     "year":2009,
     "value":"2307727390.0"
    },
    {
     "year":2010,
     "value":"2326229039.0"
    },
    {
     "year":2011,
     "value":"2344831218.0"
    },
    {
     "year":2012,
     "value":"2362963724.0"
    },
    {
     "year":2013,
     "value":"2383898490.0"
    },
    {
     "year":2014,
     "value":"2404401657.0"
    },
    {
     "year":2015,
     "value":"2425228681.0"
    },
    {
     "year":2016,
     "value":"2444346641.0"
    },
    {
     "year":2017,
     "value":"2462191613.0"
    },
    {
     "year":2018,
     "value":"2480017914.0"
    },
    {
     "year":2019,
     "value":"2494907340.0"
    },
    {
     "year":2020,
     "value":"2507920871.0"
    },
    {
     "year":2021,
     "value":"2517033423.0"
    }
   ]
  },
  {
   "indicator":"Rural Population, total",
   "yearlyData":[
    {
     "year":1980,
     "value":"1062455201.0"
    },
    {
     "year":1981,
     "value":"1065997873.0"
    },
    {
     "year":1982,
     "value":"1070581098.0"
    },
    {
     "year":1983,
     "value":"1076352695.0"
    },
    {
     "year":1984,
     "value":"1080856263.0"
    },
    {
     "year":1985,
     "value":"1085494389.0"
    },
    {
     "year":1986,
     "value":"1091013257.0"
    },
    {
     "year":1987,
     "value":"1097329281.0"
    },
    {
     "year":1988,
     "value":"1103439310.0"
    },
    {
     "year":1989,
     "value":"1108815232.0"
    },
    {
     "year":1990,
     "value":"1113617963.0"
    },
    {
     "year":1991,
     "value":"1116237990.0"
    },
    {
     "year":1992,
     "value":"1117144632.0"
    },
    {
     "year":1993,
     "value":"1116969918.0"
    },
    {
     "year":1994,
     "value":"1116157995.0"
    },
    {
     "year":1995,
     "value":"1114390757.0"
    },
    {
     "year":1996,
     "value":"1112025369.0"
    },
    {
     "year":1997,
     "value":"1108941098.0"
    },
    {
     "year":1998,
     "value":"1104767814.0"
    },
    {
     "year":1999,
     "value":"1099304857.0"
    },
    {
     "year":2000,
     "value":"1092514230.0"
    },
    {
     "year":2001,
     "value":"1082377436.0"
    },
    {
     "year":2002,
     "value":"1070002307.0"
    },
    {
     "year":2003,
     "value":"1056657122.0"
    },
    {
     "year":2004,
     "value":"1042604912.0"
    },
    {
     "year":2005,
     "value":"1028079178.0"
    },
    {
     "year":2006,
     "value":"1013319499.0"
    },
    {
     "year":2007,
     "value":"998143240.0"
    },
    {
     "year":2008,
     "value":"982922866.0"
    },
    {
     "year":2009,
     "value":"967598085.0"
    },
    {
     "year":2010,
     "value":"951772129.0"
    },
    {
     "year":2011,
     "value":"937364947.0"
    },
    {
     "year":2012,
     "value":"924312014.0"
    },
    {
     "year":2013,
     "value":"911274533.0"
    },
    {
     "year":2014,
     "value":"897799198.0"
    },
    {
     "year":2015,
     "value":"883832715.0"
    },
    {
     "year":2016,
     "value":"869302685.0"
    },
    {
     "year":2017,
     "value":"854664094.0"
    },
    {
     "year":2018,
     "value":"839509157.0"
    },
    {
     "year":2019,
     "value":"823954110.0"
    },
    {
     "year":2020,
     "value":"807856520.0"
    },
    {
     "year":2021,
     "value":"791042816.0"
    }
   ]
  },
  {
   "indicator":"Urban Population, total",
   "yearlyData":[
    {
     "year":1980,
     "value":"584367270.0"
    },
    {
     "year":1981,
     "value":"605599814.0"
    },
    {
     "year":1982,
     "value":"627915036.0"
    },
    {
     "year":1983,
     "value":"649262517.0"
    },
    {
     "year":1984,
     "value":"671087009.0"
    },
    {
     "year":1985,
     "value":"693422053.0"
    },
    {
     "year":1986,
     "value":"716500410.0"
    },
    {
     "year":1987,
     "value":"740443248.0"
    },
    {
     "year":1988,
     "value":"764826670.0"
    },
    {
     "year":1989,
     "value":"788781253.0"
    },
    {
     "year":1990,
     "value":"812198806.0"
    },
    {
     "year":1991,
     "value":"836760110.0"
    },
    {
     "year":1992,
     "value":"861003509.0"
    },
    {
     "year":1993,
     "value":"885480666.0"
    },
    {
     "year":1994,
     "value":"910469299.0"
    },
    {
     "year":1995,
     "value":"935500351.0"
    },
    {
     "year":1996,
     "value":"960793865.0"
    },
    {
     "year":1997,
     "value":"986405432.0"
    },
    {
     "year":1998,
     "value":"1012252402.0"
    },
    {
     "year":1999,
     "value":"1038038326.0"
    },
    {
     "year":2000,
     "value":"1063986983.0"
    },
    {
     "year":2001,
     "value":"1092331859.0"
    },
    {
     "year":2002,
     "value":"1122092954.0"
    },
    {
     "year":2003,
     "value":"1152196669.0"
    },
    {
     "year":2004,
     "value":"1182729885.0"
    },
    {
     "year":2005,
     "value":"1213751340.0"
    },
    {
     "year":2006,
     "value":"1244220885.0"
    },
    {
     "year":2007,
     "value":"1274334502.0"
    },
    {
     "year":2008,
     "value":"1305264310.0"
    },
    {
     "year":2009,
     "value":"1336774453.0"
    },
    {
     "year":2010,
     "value":"1368245706.0"
    },
    {
     "year":2011,
     "value":"1399498063.0"
    },
    {
     "year":2012,
     "value":"1431823667.0"
    },
    {
     "year":2013,
     "value":"1465171083.0"
    },
    {
     "year":2014,
     "value":"1498951663.0"
    },
    {
     "year":2015,
     "value":"1532338785.0"
    },
    {
     "year":2016,
     "value":"1564963701.0"
    },
    {
     "year":2017,
     "value":"1597344399.0"
    },
    {
     "year":2018,
     "value":"1628494865.0"
    },
    {
     "year":2019,
     "value":"1658181075.0"
    },
    {
     "year":2020,
     "value":"1685638790.0"
    },
    {
     "year":2021,
     "value":"1710307508.0"
    }
   ]
  },
  {
   "indicator":"Unemployment, youth total (% of total labor force ages 15-24) (modeled ILO estimate)",
   "yearlyData":[
    {
     "year":1991,
     "value":"7.55628834791089"
    },
    {
     "year":1992,
     "value":"7.71939201246417"
    },
    {
     "year":1993,
     "value":"8.421679292855881"
    },
    {
     "year":1994,
     "value":"9.24486169596978"
    },
    {
     "year":1995,
     "value":"10.269046314707301"
    },
    {
     "year":1996,
     "value":"10.747935065941801"
    },
    {
     "year":1997,
     "value":"11.253371264519696"
    },
    {
     "year":1998,
     "value":"11.992759541433198"
    },
    {
     "year":1999,
     "value":"12.257827574950099"
    },
    {
     "year":2000,
     "value":"12.040629149028804"
    },
    {
     "year":2001,
     "value":"12.536001933568599"
    },
    {
     "year":2002,
     "value":"13.116555409319801"
    },
    {
     "year":2003,
     "value":"13.538581137991901"
    },
    {
     "year":2004,
     "value":"13.2399444046046"
    },
    {
     "year":2005,
     "value":"13.040043057583402"
    },
    {
     "year":2006,
     "value":"12.602517269207802"
    },
    {
     "year":2007,
     "value":"12.228425248510801"
    },
    {
     "year":2008,
     "value":"12.4549820745155"
    },
    {
     "year":2009,
     "value":"13.583944583066799"
    },
    {
     "year":2010,
     "value":"13.1459265356101"
    },
    {
     "year":2011,
     "value":"12.818539642149501"
    },
    {
     "year":2012,
     "value":"12.7951159449647"
    },
    {
     "year":2013,
     "value":"12.968589604941599"
    },
    {
     "year":2014,
     "value":"13.2222945818501"
    },
    {
     "year":2015,
     "value":"13.8401673302284"
    },
    {
     "year":2016,
     "value":"14.7366414765959"
    },
    {
     "year":2017,
     "value":"14.8489821263524"
    },
    {
     "year":2018,
     "value":"14.625655345088502"
    },
    {
     "year":2019,
     "value":"15.4764702653071"
    },
    {
     "year":2020,
     "value":"17.4900844808928"
    },
    {
     "year":2021,
     "value":"16.8631882213769"
    },
    {
     "year":2022,
     "value":"15.9513825430597"
    }
   ]
  },
  {
   "indicator":"Used a mobile phone or the internet to access an account, income, poorest 40% (% ages 15+)",
   "yearlyData":[
    {
     "year":2017,
     "value":"0.1646605134010315"
    }
   ]
  },
  {
   "indicator":"Used a mobile phone or the internet to access an account, income, richest 60% (% ages 15+)",
   "yearlyData":[
    {
     "year":2017,
     "value":"0.3909145593643189"
    }
   ]
  },
  {
   "indicator":"Used a mobile phone or the internet to access an account, young (% ages 15-24)",
   "yearlyData":[
    {
     "year":2017,
     "value":"0.3596826493740082"
    }
   ]
  },
  {
   "indicator":"Used a mobile phone or the internet to access an account, older (% age 25+)",
   "yearlyData":[
    {
     "year":2017,
     "value":"0.2836815118789673"
    }
   ]
  }
 ]
}