{
 "Alpha-3 code":"BLM",
 "Country or Area":"Saint Barth\u00e9lemy",
 "Latitude (average)":17.9,
 "Longitude (average)":-62.8333,
 "Group 1":"Americas",
 "Group 2":"Latin America and the Caribbean",
 "LDC":false,
 "LLDC":false,
 "SIDS":false,
 "Income group":"",
 "UNDP_Region":"",
 "indicators":[
  {
   "indicator":"Climate Change-related change in death rates per 100,000 population (RCP4.5 SSP3)",
   "yearlyData":[
    {
     "year":2030,
     "value":-1.77
    },
    {
     "year":2040,
     "value":-4.31
    },
    {
     "year":2090,
     "value":-4.46
    }
   ]
  },
  {
   "indicator":"Climate Change-related change in death rates per 100,000 population (RCP8.5 SSP3)",
   "yearlyData":[
    {
     "year":2030,
     "value":-2.97
    },
    {
     "year":2040,
     "value":-6.95
    },
    {
     "year":2090,
     "value":-12.37
    }
   ]
  },
  {
   "indicator":"Coverage of protected areas in relation to marine areas",
   "yearlyData":[
    {
     "year":2000,
     "value":25.73
    },
    {
     "year":2001,
     "value":25.73
    },
    {
     "year":2002,
     "value":25.73
    },
    {
     "year":2003,
     "value":25.73
    },
    {
     "year":2004,
     "value":25.73
    },
    {
     "year":2005,
     "value":25.73
    },
    {
     "year":2006,
     "value":25.73
    },
    {
     "year":2007,
     "value":25.77
    },
    {
     "year":2008,
     "value":25.77
    },
    {
     "year":2009,
     "value":25.77
    },
    {
     "year":2010,
     "value":75.71
    },
    {
     "year":2011,
     "value":75.71
    },
    {
     "year":2012,
     "value":75.71
    },
    {
     "year":2013,
     "value":75.71
    },
    {
     "year":2014,
     "value":75.71
    },
    {
     "year":2015,
     "value":75.71
    },
    {
     "year":2016,
     "value":75.71
    },
    {
     "year":2017,
     "value":75.71
    },
    {
     "year":2018,
     "value":75.71
    },
    {
     "year":2019,
     "value":75.71
    },
    {
     "year":2020,
     "value":75.71
    },
    {
     "year":2021,
     "value":75.71
    },
    {
     "year":2022,
     "value":75.71
    },
    {
     "year":2023,
     "value":75.71
    }
   ]
  },
  {
   "indicator":"Cumulative Number of COVID-19 Cases",
   "yearlyData":[
    {
     "year":2020,
     "value":189.0
    },
    {
     "year":2021,
     "value":1726.0
    },
    {
     "year":2022,
     "value":5402.0
    },
    {
     "year":2023,
     "value":5507.0
    },
    {
     "year":2024,
     "value":5507.0
    }
   ]
  },
  {
   "indicator":"Cumulative Number of COVID-19 Deaths",
   "yearlyData":[
    {
     "year":2020,
     "value":0.0
    },
    {
     "year":2021,
     "value":4.0
    },
    {
     "year":2022,
     "value":5.0
    },
    {
     "year":2023,
     "value":5.0
    },
    {
     "year":2024,
     "value":5.0
    }
   ]
  },
  {
   "indicator":"Installed renewable electricity-generating capacity (watts per capita)",
   "yearlyData":[
    {
     "year":2000,
     "value":0.0
    },
    {
     "year":2001,
     "value":0.0
    },
    {
     "year":2002,
     "value":0.0
    },
    {
     "year":2003,
     "value":0.0
    },
    {
     "year":2004,
     "value":0.0
    },
    {
     "year":2005,
     "value":0.0
    },
    {
     "year":2006,
     "value":0.0
    },
    {
     "year":2007,
     "value":0.0
    },
    {
     "year":2008,
     "value":0.0
    },
    {
     "year":2009,
     "value":0.0
    },
    {
     "year":2010,
     "value":0.0
    },
    {
     "year":2011,
     "value":0.0
    },
    {
     "year":2012,
     "value":0.0
    },
    {
     "year":2013,
     "value":0.0
    },
    {
     "year":2014,
     "value":0.0
    },
    {
     "year":2015,
     "value":0.0
    },
    {
     "year":2016,
     "value":2.46
    },
    {
     "year":2017,
     "value":2.45
    },
    {
     "year":2018,
     "value":2.44
    },
    {
     "year":2019,
     "value":2.44
    },
    {
     "year":2020,
     "value":2.43
    }
   ]
  },
  {
   "indicator":"Installed electricity capacity (MW) by Country\/area",
   "yearlyData":[
    {
     "year":2011,
     "value":37.2
    },
    {
     "year":2012,
     "value":37.2
    },
    {
     "year":2013,
     "value":68.4
    },
    {
     "year":2014,
     "value":68.4
    },
    {
     "year":2015,
     "value":68.4
    },
    {
     "year":2016,
     "value":68.42
    },
    {
     "year":2017,
     "value":68.42
    },
    {
     "year":2018,
     "value":68.42
    },
    {
     "year":2019,
     "value":68.42
    },
    {
     "year":2020,
     "value":68.42
    }
   ]
  },
  {
   "indicator":"Proportion of forest area within legally established protected areas (%)",
   "yearlyData":[
    {
     "year":2000,
     "value":0.0
    },
    {
     "year":2010,
     "value":0.0
    },
    {
     "year":2015,
     "value":0.0
    },
    {
     "year":2016,
     "value":0.0
    },
    {
     "year":2017,
     "value":0.0
    },
    {
     "year":2018,
     "value":0.0
    },
    {
     "year":2019,
     "value":0.0
    },
    {
     "year":2020,
     "value":0.0
    }
   ]
  },
  {
   "indicator":"Proportion of forest area with a long-term management plan",
   "yearlyData":[
    {
     "year":2000,
     "value":0.0
    },
    {
     "year":2010,
     "value":0.0
    },
    {
     "year":2015,
     "value":0.0
    },
    {
     "year":2016,
     "value":0.0
    },
    {
     "year":2017,
     "value":0.0
    },
    {
     "year":2018,
     "value":0.0
    },
    {
     "year":2019,
     "value":0.0
    },
    {
     "year":2020,
     "value":0.0
    }
   ]
  },
  {
   "indicator":"COVID-19 Fatality Rate",
   "yearlyData":[
    {
     "year":2020,
     "value":0.0
    },
    {
     "year":2021,
     "value":0.23
    },
    {
     "year":2022,
     "value":0.09
    },
    {
     "year":2023,
     "value":0.09
    },
    {
     "year":2024,
     "value":0.09
    }
   ]
  },
  {
   "indicator":"Population, total",
   "yearlyData":[
    {
     "year":1980,
     "value":2983.0
    },
    {
     "year":1981,
     "value":3035.0
    },
    {
     "year":1982,
     "value":3201.0
    },
    {
     "year":1983,
     "value":3483.0
    },
    {
     "year":1984,
     "value":3756.0
    },
    {
     "year":1985,
     "value":4016.0
    },
    {
     "year":1986,
     "value":4263.0
    },
    {
     "year":1987,
     "value":4505.0
    },
    {
     "year":1988,
     "value":4742.0
    },
    {
     "year":1989,
     "value":4964.0
    },
    {
     "year":1990,
     "value":5168.0
    },
    {
     "year":1991,
     "value":5365.0
    },
    {
     "year":1992,
     "value":5562.0
    },
    {
     "year":1993,
     "value":5762.0
    },
    {
     "year":1994,
     "value":5956.0
    },
    {
     "year":1995,
     "value":6144.0
    },
    {
     "year":1996,
     "value":6334.0
    },
    {
     "year":1997,
     "value":6524.0
    },
    {
     "year":1998,
     "value":6710.0
    },
    {
     "year":1999,
     "value":6895.0
    },
    {
     "year":2000,
     "value":7082.0
    },
    {
     "year":2001,
     "value":7271.0
    },
    {
     "year":2002,
     "value":7463.0
    },
    {
     "year":2003,
     "value":7655.0
    },
    {
     "year":2004,
     "value":7848.0
    },
    {
     "year":2005,
     "value":8044.0
    },
    {
     "year":2006,
     "value":8237.0
    },
    {
     "year":2007,
     "value":8430.0
    },
    {
     "year":2008,
     "value":8623.0
    },
    {
     "year":2009,
     "value":8816.0
    },
    {
     "year":2010,
     "value":8988.0
    },
    {
     "year":2011,
     "value":9108.0
    },
    {
     "year":2012,
     "value":9216.0
    },
    {
     "year":2013,
     "value":9338.0
    },
    {
     "year":2014,
     "value":9472.0
    },
    {
     "year":2015,
     "value":9643.0
    },
    {
     "year":2016,
     "value":9842.0
    },
    {
     "year":2017,
     "value":10044.0
    },
    {
     "year":2018,
     "value":10258.0
    },
    {
     "year":2019,
     "value":10480.0
    },
    {
     "year":2020,
     "value":10681.0
    },
    {
     "year":2021,
     "value":10861.0
    },
    {
     "year":2022,
     "value":10967.0
    },
    {
     "year":2023,
     "value":10994.0
    },
    {
     "year":2024,
     "value":11019.0
    }
   ]
  }
 ]
}